cloudsms/__init__.py
cloudsms/client.py
cloudsms-1.0.1.dist-info/METADATA
cloudsms-1.0.1.dist-info/WHEEL
cloudsms-1.0.1.dist-info/top_level.txt
cloudsms-1.0.1.dist-info/RECORD
